griffe_tui-1.0.0.dist-info/METADATA
griffe_tui-1.0.0.dist-info/WHEEL
griffe_tui-1.0.0.dist-info/entry_points.txt
griffe_tui-1.0.0.dist-info/licenses/LICENSE
griffe_tui/__init__.py
griffe_tui/__main__.py
griffe_tui/app.py
griffe_tui/cli.py
griffe_tui/debug.py
griffe_tui/markdown.py
griffe_tui/py.typed
griffe_tui/tcss/griffe_tui.tcss
griffe_tui-1.0.0.dist-info/RECORD
