Metadata-Version: 2.1
Name: griffe-tui
Version: 1.0.0
Summary: A textual user interface for Griffe.
Author-Email: =?utf-8?q?Timoth=C3=A9e_Mazzucotelli?= <dev@pawamoy.fr>
License: ISC
Classifier: Development Status :: 4 - Beta
Classifier: Intended Audience :: Developers
Classifier: Programming Language :: Python
Classifier: Programming Language :: Python :: 3
Classifier: Programming Language :: Python :: 3 :: Only
Classifier: Programming Language :: Python :: 3.9
Classifier: Programming Language :: Python :: 3.10
Classifier: Programming Language :: Python :: 3.11
Classifier: Programming Language :: Python :: 3.12
Classifier: Programming Language :: Python :: 3.13
Classifier: Programming Language :: Python :: 3.14
Classifier: Topic :: Documentation
Classifier: Topic :: Software Development
Classifier: Topic :: Utilities
Classifier: Typing :: Typed
Project-URL: Homepage, https://mkdocstrings.github.io/griffe-tui
Project-URL: Documentation, https://mkdocstrings.github.io/griffe-tui
Project-URL: Changelog, https://mkdocstrings.github.io/griffe-tui/changelog
Project-URL: Repository, https://github.com/mkdocstrings/griffe-tui
Project-URL: Issues, https://github.com/mkdocstrings/griffe-tui/issues
Project-URL: Discussions, https://github.com/mkdocstrings/griffe-tui/discussions
Project-URL: Gitter, https://gitter.im/mkdocstrings/griffe-tui
Project-URL: Funding, https://github.com/sponsors/pawamoy
Requires-Python: >=3.9
Requires-Dist: textual>=0.36
Requires-Dist: griffe2md>=1.0.1
Requires-Dist: importlib-metadata>=4.6; python_version < "3.10"
